ELSPy/ELS.py
ELSPy/__init__.py
ELSPy-0.1.1.dist-info/METADATA
ELSPy-0.1.1.dist-info/WHEEL
ELSPy-0.1.1.dist-info/top_level.txt
ELSPy-0.1.1.dist-info/RECORD
