Metadata-Version: 2.1
Name: ELSPy
Version: 0.1.1
Summary: Electrolux Laundry System Python utility package
Home-page: https://github.com/ruuti/ELSPy
Author: Miikka Värri
Author-email: miikka.varri@gmail.com
License: UNKNOWN
Platform: any
Classifier: Programming Language :: Python :: 3
Classifier: License :: OSI Approved :: MIT License
Classifier: Operating System :: OS Independent
Requires-Python: >=3
Requires-Dist: zeep (>=3.2.0)
